<theme>
   <variables>
      <systemDescription>View and play all of your favorite game ports.</systemDescription>
      <systemManufacturer>Various</systemManufacturer>
      <systemReleaseYear>Various</systemReleaseYear>
      <systemReleaseDate>Various</systemReleaseDate>
      <systemReleaseDateFormated>Various</systemReleaseDateFormated>
      <systemHardwareType>Folder</systemHardwareType>
      <systemColor>2d62c1</systemColor>
      <systemColorPalette1>4F5054</systemColorPalette1>
      <systemColorPalette2>737375</systemColorPalette2>
      <systemColorPalette3>F4BE46</systemColorPalette3>
      <systemColorPalette4>E45B12</systemColorPalette4>
   </variables>
</theme>